bidcap/__init__.py
bidcap/setup.py
bidcap/datasets/__init__.py
bidcap/datasets/convex.py
bidcap/datasets/data.py
bidcap/datasets/mnist.py
bidcap/utils/__init__.py
bidcap/utils/loader.py
bidcap-0.0.1.dist-info/METADATA
bidcap-0.0.1.dist-info/RECORD
bidcap-0.0.1.dist-info/WHEEL
bidcap-0.0.1.dist-info/top_level.txt
