Metadata-Version: 2.1
Name: bidcap
Version: 0.0.1
Summary: benchmark image dataset collection and preprocessing
Home-page: https://github.com/wwwbbb8510/bidcap.git
Author: Bin Wang
Author-email: wwwbbb8510@gmail.com
License: UNKNOWN
Platform: UNKNOWN
Classifier: Programming Language :: Python :: 3
Classifier: License :: OSI Approved :: MIT License
Classifier: Operating System :: OS Independent
